MANIFEST.in
README.md
setup.py
aos_tools.egg-info/PKG-INFO
aos_tools.egg-info/SOURCES.txt
aos_tools.egg-info/dependency_links.txt
aos_tools.egg-info/entry_points.txt
aos_tools.egg-info/requires.txt
aos_tools.egg-info/top_level.txt
aostools/__init__.py
aostools/builder.py
aostools/cmd.py
aostools/command.py
aostools/component.py
aostools/gitproject.py
aostools/log.py
aostools/make.py
aostools/manifest.py
aostools/occ.py
aostools/package.py
aostools/progress.py
aostools/qemu.py
aostools/repo.py
aostools/solution.py
aostools/toolchain.py
aostools/tools.py
aostools/yoc.py
aostools/build/gen_ldfile.sh
aostools/build/product32
aostools/build/product64
aostools/script/aft_build.sh
aostools/script/cdkgdbinit
aostools/script/flash.init
aostools/script/flash_prog.init
aostools/script/pre_build.sh
aostools/site_tools/__init__.py
aostools/site_tools/objcopy.py
aostools/site_tools/objdump.py
aostools/site_tools/product.py
aostools/subcmds/__init__.py
aostools/subcmds/addkey.py
aostools/subcmds/branch.py
aostools/subcmds/burn.py
aostools/subcmds/cct.py
aostools/subcmds/cdk.py
aostools/subcmds/checkout.py
aostools/subcmds/config.py
aostools/subcmds/convert.py
aostools/subcmds/copy.py
aostools/subcmds/cpu.py
aostools/subcmds/debug.py
aostools/subcmds/export.py
aostools/subcmds/exportall.py
aostools/subcmds/format.py
aostools/subcmds/generate.py
aostools/subcmds/help.py
aostools/subcmds/init.py
aostools/subcmds/install.py
aostools/subcmds/list.py
aostools/subcmds/make.py
aostools/subcmds/monitor.py
aostools/subcmds/pack.py
aostools/subcmds/protect.py
aostools/subcmds/rename.py
aostools/subcmds/sdk.py
aostools/subcmds/search.py
aostools/subcmds/show.py
aostools/subcmds/sync.py
aostools/subcmds/toolchain.py
aostools/subcmds/uninstall.py
aostools/subcmds/upgrade.py
aostools/subcmds/upload.py
aostools/subcmds/users.py
aostools/subcmds/variable.py
aostools/subcmds/create/__init__.py
aostools/subcmds/create/create.py
aostools/subcmds/create/project.py
git/__init__.py
git/cmd.py
git/compat.py
git/config.py
git/db.py
git/diff.py
git/exc.py
git/remote.py
git/util.py
git/index/__init__.py
git/index/base.py
git/index/fun.py
git/index/typ.py
git/index/util.py
git/objects/__init__.py
